<?xml version="1.0" encoding="utf-8" ?>
<dwsync>
<file name="CacheControlFilter.java" server="psyko.me//public_html/" local="131041888620000000" remote="131146740600000000" Dst="2" />
<file name="CahModule.java" server="psyko.me//public_html/" local="131041888620000000" remote="131146740600000000" Dst="2" />
<file name="Constants.java" server="psyko.me//public_html/" local="131041888620000000" remote="131146740600000000" Dst="2" />
<file name="HibernateUtil.java" server="psyko.me//public_html/" local="131041888620000000" remote="131146740600000000" Dst="2" />
<file name="JsonWrapper.java" server="psyko.me//public_html/" local="131041888620000000" remote="131146740600000000" Dst="2" />
<file name="RequestWrapper.java" server="psyko.me//public_html/" local="131041888620000000" remote="131146740600000000" Dst="2" />
<file name="Server.java" server="psyko.me//public_html/" local="131041888620000000" remote="131146740600000000" Dst="2" />
<file name="StartupUtils.java" server="psyko.me//public_html/" local="131041888620000000" remote="131146740600000000" Dst="2" />
<file name="UpdateHandlerList.cmd" server="psyko.me//public_html/" local="131041888620000000" remote="131146740600000000" Dst="2" />
<file name="UpdateHandlerList.java" server="psyko.me//public_html/" local="131041888620000000" remote="131146740600000000" Dst="2" />
<file name="UpdateJsConstants.cmd" server="psyko.me//public_html/" local="131041888620000000" remote="131146740600000000" Dst="2" />
<file name="UpdateJsConstants.java" server="psyko.me//public_html/" local="131041888620000000" remote="131146740600000000" Dst="2" />
</dwsync>